[
    {
        "id": 86,
        "url": "https://pub-7ef623b87169458aaafb3a91ab9b2966.r2.dev/full/20211216_绿洲_XZ.jpg",
        "date": "2021-12-16",
        "month": "December",
        "year": "2021",
        "tags": [
            "剧透",
            "蜘蛛侠"
        ],
        "category": "screenshot",
        "source": "oasis",
        "groupName": "202112",
        "photoText": "X玖少年团肖战DAYTOY\n不小心看到蜘蛛侠剧透的我\n发布于2021/12/16 14:36\n在绿洲,遇见美好遇见你"
    },
    {
        "id": 87,
        "url": "https://pub-7ef623b87169458aaafb3a91ab9b2966.r2.dev/full/20211216_绿洲-P_XZ-1.jpg",
        "date": "2021-12-16",
        "month": "December",
        "year": "2021",
        "tags": [
            "表情包",
            "狗"
        ],
        "link": "",
        "groupName": "202112",
        "note": "",
        "category": "attached",
        "source": "oasis",
        "photoText": ""
    },
    {
        "id": 85,
        "url": "https://pub-7ef623b87169458aaafb3a91ab9b2966.r2.dev/full/20211117_DY_XZ.mp4",
        "date": "2021-11-17",
        "month": "November",
        "year": "2021",
        "tags": [
            "Video",
            "😏"
        ],
        "category": "attached",
        "source": "douyin",
        "link": "https://v.douyin.com/omTtBKlfImY/",
        "groupName": "202111",
        "photoText": ""
    },
    {
        "id": 80,
        "url": "https://pub-7ef623b87169458aaafb3a91ab9b2966.r2.dev/full/20211017_绿洲_XZ.jpg",
        "date": "2021-10-17",
        "month": "October",
        "year": "2021",
        "tags": [
            "如梦之梦",
            "杭州"
        ],
        "category": "screenshot",
        "source": "oasis",
        "groupName": "202110",
        "photoText": "X玖少年团肖战DAYTOY\n人的夢想是不會結束的\nDreams never end\n第十帖\n閃閃發亮的大人\n所闻所想\n发布于2021/10/17 10:10\n在绿洲,遇见美好遇见你"
    },
    {
        "id": 81,
        "url": "https://pub-7ef623b87169458aaafb3a91ab9b2966.r2.dev/full/20211017_绿洲-P_XZ-2.jpg",
        "date": "2021-10-17",
        "month": "October",
        "year": "2021",
        "tags": [
            "如梦之梦",
            "杭州",
            "闪闪发亮的大人"
        ],
        "link": "",
        "groupName": "202110",
        "note": "",
        "category": "attached",
        "source": "oasis",
        "photoText": "第十帖\n閃閃發亮的大人"
    },
    {
        "id": 82,
        "url": "https://pub-7ef623b87169458aaafb3a91ab9b2966.r2.dev/full/20211017_绿洲-P_XZ-1.jpg",
        "date": "2021-10-17",
        "month": "October",
        "year": "2021",
        "tags": [
            "如梦之梦",
            "杭州",
            "人的梦想是不会结束的",
            "Dreams never end"
        ],
        "link": "",
        "groupName": "202110",
        "note": "",
        "category": "attached",
        "source": "oasis",
        "photoText": "人的夢想是不會結束的\nDreams never end"
    },
    {
        "id": 83,
        "url": "https://pub-7ef623b87169458aaafb3a91ab9b2966.r2.dev/full/20211017_绿洲-P_XZ-3.jpg",
        "date": "2021-10-17",
        "month": "October",
        "year": "2021",
        "tags": [
            "如梦之梦",
            "杭州",
            "摄影"
        ],
        "link": "",
        "groupName": "202110",
        "note": "",
        "category": "attached",
        "source": "oasis",
        "photoText": ""
    },
    {
        "id": 84,
        "url": "https://pub-7ef623b87169458aaafb3a91ab9b2966.r2.dev/full/20211017_绿洲-P_XZ-4.jpg",
        "date": "2021-10-17",
        "month": "October",
        "year": "2021",
        "tags": [
            "如梦之梦",
            "杭州",
            "摄影",
            "西湖"
        ],
        "link": "",
        "groupName": "202110",
        "note": "",
        "category": "attached",
        "source": "oasis",
        "photoText": ""
    },
    {
        "id": 78,
        "url": "https://pub-7ef623b87169458aaafb3a91ab9b2966.r2.dev/full/20210930_WB_XZ.jpg",
        "date": "2021-09-30",
        "month": "September",
        "year": "2021",
        "tags": [
            "国庆"
        ],
        "category": "screenshot",
        "groupName": "202109",
        "source": "weibo",
        "link": "",
        "note": "",
        "photoText": "肖战\n21-9-30 16:45 来自iPhone 13 Pro...\n马上就是国庆小长假了,提前祝大家国庆快乐!\n希望大家可以在这个假期,多多陪伴家人。同\n时,也要保护好自己和家人,非必要不出行。\n一定要做好防疫工作,避免去人多的地方,开\n心健康地度过节日!\n⑥@X玖少年团肖战DAYTOY"
    },
    {
        "id": 79,
        "url": "https://pub-7ef623b87169458aaafb3a91ab9b2966.r2.dev/full/20210930_XZ-Weibo-1.jpg",
        "date": "2021-09-30",
        "month": "September",
        "year": "2021",
        "tags": [
            "国庆",
            "摄影"
        ],
        "link": "",
        "groupName": "202109",
        "note": "",
        "category": "attached",
        "source": "weibo",
        "photoText": "@X玖少年团肖战DAYTOY"
    },
    {
        "id": 75,
        "url": "https://pub-7ef623b87169458aaafb3a91ab9b2966.r2.dev/full/20210925-1_绿洲_XZ.jpg",
        "date": "2021-09-25",
        "month": "September",
        "year": "2021",
        "tags": [
            "随笔",
            "如梦之梦"
        ],
        "category": "screenshot",
        "groupName": "202109",
        "source": "oasis",
        "link": "",
        "note": "",
        "photoText": "12:10\n<所有 iCloud\n2021年9月25日 上午12:10\n5G\n三个月没有走上如梦的舞台了。静谧的剧\n场,安静的座椅一切依旧。\n舞台上有五号入梦的故事,也有每一个动人\n的角色与彼此交互的故事。这股能量,打动\n台前幕后的每一位演职人员,相信也打动着\n在场的每一位。用眼睛、用全心去记录去感\n受吧!同一时空中的浸润和感动,全心去感\n受,不需多言。\n感谢大家谢幕时的掌声,这是对每个人用心\n呈现的舞台最好的鼓励和认可。\n也希望这一刻的感动无关其他,只是关于如\n梦之梦的故事。"
    },
    {
        "id": 76,
        "url": "https://pub-7ef623b87169458aaafb3a91ab9b2966.r2.dev/full/20210925_绿洲_XZ.jpg",
        "date": "2021-09-25",
        "month": "September",
        "year": "2021",
        "tags": [
            "随笔",
            "如梦之梦"
        ],
        "category": "screenshot",
        "groupName": "202109",
        "source": "oasis",
        "link": "",
        "note": "",
        "photoText": "X玖少年团肖战DAYTOY\n12:10\n<所有 iCloud\n2021年9月25日上午12:10\n5G\n三个月没有走上如梦的舞台了。静谧的剧\n场,安静的座椅一切依旧。\n舞台上有五号入梦的故事,也有每一个动人\n的角色与彼此交互的故事。这股能量,打动\n台前幕后的每一位演职人员,相信也打动着\n在场的每一位。用眼睛、用全心去记录去感\n受吧!同一时空中的浸润和感动,全心去感\n受,不需多言。\n感谢大家谢幕时的掌声,这是对每个人用心\n呈现的舞台最好的鼓励和认可。\n也希望这一刻的感动无关其他,只是关于如\n梦之梦的故事。\n发布于2021/09/25 00:19\n09\n在绿洲,分享美好生活\n11"
    },
    {
        "id": 77,
        "url": "https://pub-7ef623b87169458aaafb3a91ab9b2966.r2.dev/full/20210925_绿洲-P_XZ-3.jpg",
        "date": "2021-09-25",
        "month": "September",
        "year": "2021",
        "tags": [
            "舞台",
            "如梦之梦"
        ],
        "link": "",
        "groupName": "202109",
        "note": "",
        "category": "attached",
        "source": "oasis",
        "photoText": "09\n09\n11\n11\n02\n01\n09\n60\n11"
    },
    {
        "id": 70,
        "url": "https://pub-7ef623b87169458aaafb3a91ab9b2966.r2.dev/full/20210921_WB_XZ.jpg",
        "date": "2021-09-21",
        "month": "September",
        "year": "2021",
        "tags": [
            "中秋"
        ],
        "category": "screenshot",
        "groupName": "202109",
        "source": "weibo",
        "link": "",
        "note": "",
        "photoText": "肖战\n✔21-9-21 13:40 来自iPhone 12 Pro\n中秋要吃月饼!祝大家中秋节快乐!\n3333\n休假也要注意防护,保护好自己,才能开心过\n节!\n过几天如梦的演出,提前提醒大家观看时一定\n戴好口罩,不扎堆、不聚集。认真遵循防疫要\n求是对自己和他人最好的保护。\n希望大家都能和家人团团圆圆相聚,祝大家健\n康平安、开心顺意!\n@X玖少年团肖战DAYTOY\n@X玖少年团肖战DAYTOY\n@X玖少年团肖战DAYTOY"
    },
    {
        "id": 71,
        "url": "https://pub-7ef623b87169458aaafb3a91ab9b2966.r2.dev/full/20210921_XZ-Weibo-2.jpg",
        "date": "2021-09-21",
        "month": "September",
        "year": "2021",
        "tags": [
            "中秋",
            "摄影",
            "月亮"
        ],
        "link": "",
        "groupName": "202109",
        "note": "",
        "category": "attached",
        "source": "weibo",
        "photoText": "@X玖少年团肖战DAYTOY"
    },
    {
        "id": 72,
        "url": "https://pub-7ef623b87169458aaafb3a91ab9b2966.r2.dev/full/20210921_XZ-Weibo-3.jpg",
        "date": "2021-09-21",
        "month": "September",
        "year": "2021",
        "tags": [
            "中秋",
            "月饼"
        ],
        "link": "",
        "groupName": "202109",
        "note": "",
        "category": "attached",
        "source": "weibo",
        "photoText": "@X玖少年团肖战DAYTOY"
    },
    {
        "id": 73,
        "url": "https://pub-7ef623b87169458aaafb3a91ab9b2966.r2.dev/full/20210921_XZ-Weibo-4.jpg",
        "date": "2021-09-21",
        "month": "September",
        "year": "2021",
        "tags": [
            "中秋",
            "月饼"
        ],
        "link": "",
        "groupName": "202109",
        "note": "",
        "category": "attached",
        "source": "weibo",
        "photoText": "@X玖少年团肖战DAYTOY"
    },
    {
        "id": 74,
        "url": "https://pub-7ef623b87169458aaafb3a91ab9b2966.r2.dev/full/20210921_XZ-Weibo-1.jpg",
        "date": "2021-09-21",
        "month": "September",
        "year": "2021",
        "tags": [
            "中秋",
            "月饼"
        ],
        "link": "",
        "groupName": "202109",
        "note": "",
        "category": "attached",
        "source": "weibo",
        "photoText": "@X玖少年团肖战DAYTOY"
    },
    {
        "id": 68,
        "url": "https://pub-7ef623b87169458aaafb3a91ab9b2966.r2.dev/full/20210910_WB_XZ.jpg",
        "date": "2021-09-10",
        "month": "September",
        "year": "2021",
        "tags": [
            "杭州亚运会",
            "公益圆梦大使"
        ],
        "category": "screenshot",
        "groupName": "202109",
        "source": "weibo",
        "link": "",
        "note": "",
        "photoText": "肖战\n✔ 21-9-10 20:40 来自iPhone 12 Pro\n我是杭州亚运会新任公益圆梦大使肖战。从倒\n计时1000天到倒计时1周年,今天既是#寻找\n2022个亚运梦想#大型公益行动迈向高潮的号\n角,也是我正式参与亚运公益的开始。让我们\n为梦想赋能助力,点亮更多人的生活,为亚运\n塑造属于公益的记忆,携梦同行,助梦成真\n@杭州2022年亚运会:刚刚,#肖战献唱杭州亚运\n会倒计时一周年#《我们都将奔赴美好未来》。#\n杭州亚运会圆梦公益大使肖战#青年演员、歌手肖\n战成为杭州亚运会公益圆梦大使!在杭州亚运会倒\n计时一周年之际,杭州亚组委将携手肖战及其他公\n益圆梦大使一起#寻找2022个亚运梦想#———向梦\n而行,让梦花开\n19th Asian Games\nHangzhou 2022\n寻找2022个亚运梦想\n杭州亚运会公益圆梦大使\n青年演员、歌手\n肖战\n感谢梦想\n让我全力以赴\n99\n“坚定前行\n你在追寻梦想 我在寻找你!"
    },
    {
        "id": 69,
        "url": "https://pub-7ef623b87169458aaafb3a91ab9b2966.r2.dev/full/20210910_XZ-Weibo-3.jpg",
        "date": "2021-09-10",
        "month": "September",
        "year": "2021",
        "tags": [
            "杭州亚运会",
            "公益圆梦大使"
        ],
        "groupName": "202109",
        "category": "attached",
        "source": "weibo",
        "link": "",
        "note": "",
        "photoText": "19th Asian Games\nHangzhou 2022\n寻找2022个亚运梦想\n杭州亚运会公益圆梦大使\n青年演员、歌手\n肖战\n感谢梦想\n让我全力以赴\n“坚定前你!\n你在追寻梦想 我在寻找你!"
    },
    {
        "id": 66,
        "url": "https://pub-7ef623b87169458aaafb3a91ab9b2966.r2.dev/full/20210905_WB_XZ.jpg",
        "date": "2021-09-05",
        "month": "September",
        "year": "2021",
        "tags": [
            "余生请多指教",
            "改档"
        ],
        "category": "screenshot",
        "source": "weibo",
        "groupName": "202109",
        "link": "",
        "note": "",
        "photoText": "肖战\n21-9-5 15:03 来自iPhone 12 Pro\n感谢大家关注,感谢大家和我一样理解与支持\n作品正常的排播调整。\n我曾说羡慕老顾的一切。如果用花来书写他的\n人生,那生活中一定种满了向日葵。我爱这样\n的人生,也希望大家都像这样向阳而生。感谢\n你们,让等待的过程也很美好。\n未来,请大家继续响应“清朗”行动的号召。我\n们一起,为建设和维护良好的网络环境贡献自\n己的一份力量。也希望大家能积极充实地迎接\n美好生活,脚踏实地,过好自己的每一天!\n向阳而生\n静候余生\n@X玖少年团肖战DAYTOY\nZ."
    },
    {
        "id": 67,
        "url": "https://pub-7ef623b87169458aaafb3a91ab9b2966.r2.dev/full/20210905_XZ-Weibo-1.jpg",
        "date": "2021-09-05",
        "month": "September",
        "year": "2021",
        "tags": [
            "余生请多指教",
            "改档",
            "向阳而生",
            "画"
        ],
        "link": "",
        "groupName": "202109",
        "note": "",
        "category": "attached",
        "source": "weibo",
        "photoText": "@X玖少年团肖战DAYTOY"
    },
    {
        "id": 65,
        "url": "https://pub-7ef623b87169458aaafb3a91ab9b2966.r2.dev/full/20210826_WB_XZ.jpg",
        "date": "2021-08-26",
        "month": "August",
        "year": "2021",
        "tags": [
            "倡议书"
        ],
        "category": "screenshot",
        "groupName": "202108",
        "source": "weibo",
        "link": "",
        "note": "",
        "photoText": "肖战\n21-8-26 22:27 来自iPhone 12 Pro\n作为公众人物,希望能给大家带来更多正能量\n和正向的引导,也希望大家和我一起积极响应\n国家网信办“清朗”系列专项行动号召。从自身\n做起,文明上网、理性表达,为维护良好的网\n络秩序贡献自己的一份力量!\n@肖战工作室:倡议书\n良好健康的网络环境,需要我们共同来维护。肖战\n先生及肖战工作室,都会积极响应网信办“清朗”\n系列专项行动号召。我们有义务有责任发出声音、\n表达态度,给所有关注我们的朋友们正向的引导。\n在此,我们向大家发出如下倡议:\n1,文明上网,抵制网络暴力,一同为建设健康有\n序的网络环境做出贡献。\n2,理智追星,理性讨论,坚决拒绝拉踩引战、谩\n骂互撕等不良饭圈行为。坚决抵制集资、投票打榜\n等非理性行为,化追星之爱为正能量,以积极参加\n公益活动等形式,用积极向上的态度传递给社会正\n向价值观。\n3,互联网不是法外之地,每个人都需要对自己的\n言行负责。坚决抵制用控评、披皮引战、故意内涵\n等方式干扰舆情、破坏传播秩序的违法行为。\n我们每个人都需要从自己做起,为维护良好的网络\n秩序贡献自己的一份力量。\n肖战工作室\n2021年8月26日"
    },
    {
        "id": 64,
        "url": "https://pub-7ef623b87169458aaafb3a91ab9b2966.r2.dev/full/20210824_DY_XZ.mp4",
        "date": "2021-08-24",
        "month": "August",
        "year": "2021",
        "tags": [
            "Video",
            "# 随机剪裁挑战 “找镜头？！”"
        ],
        "category": "attached",
        "groupName": "202108",
        "source": "douyin",
        "link": "https://v.douyin.com/4AHfKij-0lA/",
        "photoText": ""
    },
    {
        "id": 63,
        "url": "https://pub-7ef623b87169458aaafb3a91ab9b2966.r2.dev/full/20210811_DY_XZ.mp4",
        "date": "2021-08-11",
        "month": "August",
        "year": "2021",
        "tags": [
            "Video",
            "一些解压小物 一起# 向美好生活说你好 吧！"
        ],
        "category": "attached",
        "groupName": "202108",
        "source": "douyin",
        "link": "https://v.douyin.com/rYwB0UOeVx4/",
        "photoText": ""
    },
    {
        "id": 61,
        "url": "https://pub-7ef623b87169458aaafb3a91ab9b2966.r2.dev/full/20210714_绿洲_XZ.jpg",
        "date": "2021-07-14",
        "month": "July",
        "year": "2021",
        "tags": [
            "海绵宝宝",
            "生日快乐"
        ],
        "category": "screenshot",
        "source": "oasis",
        "groupName": "202107",
        "photoText": "X玖少年团肖战DAYTOY\n海绵宝宝\n生日快乐\n生日快乐,天天开心!\n发布于2021/07/14 12:39\n在绿洲,分享美好生活"
    },
    {
        "id": 62,
        "url": "https://pub-7ef623b87169458aaafb3a91ab9b2966.r2.dev/full/20210714_绿洲-P_XZ-1.jpg",
        "date": "2021-07-14",
        "month": "July",
        "year": "2021",
        "tags": [
            "海绵宝宝",
            "生日快乐"
        ],
        "groupName": "202107",
        "category": "attached",
        "source": "oasis",
        "photoText": "SQUAREPANTS\n海绵宝宝\n生日快乐"
    },
    {
        "id": 60,
        "url": "https://pub-7ef623b87169458aaafb3a91ab9b2966.r2.dev/full/20210713_DY_XZ.mp4",
        "date": "2021-07-13",
        "month": "July",
        "year": "2021",
        "tags": [
            "Video",
            "来了 来吗🎤"
        ],
        "category": "attached",
        "groupName": "202107",
        "source": "douyin",
        "link": "https://v.douyin.com/sIkGyzb7nXU/ ",
        "note": "",
        "photoText": ""
    },
    {
        "id": 58,
        "url": "https://pub-7ef623b87169458aaafb3a91ab9b2966.r2.dev/full/20210613_绿洲_XZ.jpg",
        "date": "2021-06-13",
        "month": "June",
        "year": "2021",
        "tags": [
            "端午",
            "画"
        ],
        "category": "screenshot",
        "source": "oasis",
        "groupName": "202106",
        "photoText": "X玖少年团肖战DAYTOY\n端\n顺顺利利\n端午安康\n发布于2021/06/13 12:20\n在绿洲,遇见美好遇见你"
    },
    {
        "id": 59,
        "url": "https://pub-7ef623b87169458aaafb3a91ab9b2966.r2.dev/full/20210613_绿洲-P_XZ-1.jpg",
        "date": "2021-06-13",
        "month": "June",
        "year": "2021",
        "tags": [
            "端午",
            "画"
        ],
        "groupName": "202106",
        "category": "attached",
        "source": "oasis",
        "photoText": "端午"
    },
    {
        "id": 57,
        "url": "https://pub-7ef623b87169458aaafb3a91ab9b2966.r2.dev/full/20210531_DY_XZ.mp4",
        "date": "2021-05-31",
        "month": "May",
        "year": "2021",
        "tags": [
            "Video",
            "🎩"
        ],
        "category": "attached",
        "groupName": "202105",
        "source": "douyin",
        "link": "https://v.douyin.com/4XaqKFRm95E/",
        "photoText": ""
    },
    {
        "id": 49,
        "url": "https://pub-7ef623b87169458aaafb3a91ab9b2966.r2.dev/full/20210529_文艺志愿者讲述焦裕禄精神_XZ.mp4",
        "date": "2021-05-29",
        "month": "May",
        "year": "2021",
        "tags": [
            "Video",
            "文艺志愿者",
            "焦裕禄"
        ],
        "category": "attached",
        "groupName": "202105",
        "photoText": ""
    },
    {
        "id": 50,
        "url": "https://pub-7ef623b87169458aaafb3a91ab9b2966.r2.dev/full/20210529_绿洲_XZ.jpg",
        "date": "2021-05-29",
        "month": "May",
        "year": "2021",
        "tags": [
            "如梦之梦",
            "海边",
            "青岛"
        ],
        "category": "screenshot",
        "groupName": "202105",
        "source": "oasis",
        "photoText": "X玖少年团肖战DAYTOY\n\"2:05 30\n\"2105 30\n\"2:05 30\n\"2:05 30\n\"2:05 30\n此刻,入梦!\n发布于2021/05/29 13:03\n在绿洲,遇见美好遇见你"
    },
    {
        "id": 51,
        "url": "https://pub-7ef623b87169458aaafb3a91ab9b2966.r2.dev/full/20210529_绿洲-P_XZ-1.jpg",
        "date": "2021-05-29",
        "month": "May",
        "year": "2021",
        "tags": [
            "如梦之梦",
            "海边",
            "青岛"
        ],
        "groupName": "202105",
        "category": "attached",
        "source": "oasis",
        "photoText": "06 05 '21\""
    },
    {
        "id": 52,
        "url": "https://pub-7ef623b87169458aaafb3a91ab9b2966.r2.dev/full/20210529_绿洲-P_XZ-2.jpg",
        "date": "2021-05-29",
        "month": "May",
        "year": "2021",
        "tags": [
            "如梦之梦",
            "海边",
            "青岛"
        ],
        "groupName": "202105",
        "category": "attached",
        "source": "oasis",
        "photoText": "06 05 '21\""
    },
    {
        "id": 53,
        "url": "https://pub-7ef623b87169458aaafb3a91ab9b2966.r2.dev/full/20210529_绿洲-P_XZ-5.jpg",
        "date": "2021-05-29",
        "month": "May",
        "year": "2021",
        "tags": [
            "如梦之梦",
            "海边",
            "青岛"
        ],
        "groupName": "202105",
        "category": "attached",
        "source": "oasis",
        "photoText": "30 05 12\""
    },
    {
        "id": 54,
        "url": "https://pub-7ef623b87169458aaafb3a91ab9b2966.r2.dev/full/20210529_绿洲-P_XZ-4.jpg",
        "date": "2021-05-29",
        "month": "May",
        "year": "2021",
        "tags": [
            "如梦之梦",
            "海边",
            "青岛"
        ],
        "groupName": "202105",
        "category": "attached",
        "source": "oasis",
        "photoText": "30 05 '21''"
    },
    {
        "id": 55,
        "url": "https://pub-7ef623b87169458aaafb3a91ab9b2966.r2.dev/full/20210529_绿洲-P_XZ-3.jpg",
        "date": "2021-05-29",
        "month": "May",
        "year": "2021",
        "tags": [
            "如梦之梦",
            "海边",
            "青岛"
        ],
        "groupName": "202105",
        "category": "attached",
        "source": "oasis",
        "photoText": "06 50 12''"
    },
    {
        "id": 56,
        "url": "https://pub-7ef623b87169458aaafb3a91ab9b2966.r2.dev/full/20210529_绿洲-P_XZ-6.jpg",
        "date": "2021-05-29",
        "month": "May",
        "year": "2021",
        "tags": [
            "如梦之梦",
            "海边",
            "青岛"
        ],
        "groupName": "202105",
        "category": "attached",
        "source": "oasis",
        "photoText": ""
    },
    {
        "id": 42,
        "url": "https://pub-7ef623b87169458aaafb3a91ab9b2966.r2.dev/full/20210527_绿洲_XZ.jpg",
        "date": "2021-05-27",
        "month": "May",
        "year": "2021",
        "tags": [
            "小面包"
        ],
        "category": "screenshot",
        "groupName": "202105",
        "source": "oasis",
        "photoText": "X玖少年团肖战DAYTOY\n不吃了不吃了不!吃了!\n发布于2021/05/27 10:05\n在绿洲,分享美好生活"
    },
    {
        "id": 43,
        "url": "https://pub-7ef623b87169458aaafb3a91ab9b2966.r2.dev/full/20210527_绿洲-P_XZ-5.jpg",
        "date": "2021-05-27",
        "month": "May",
        "year": "2021",
        "tags": [
            "表情包"
        ],
        "link": "",
        "groupName": "202105",
        "note": "",
        "category": "attached",
        "source": "oasis",
        "photoText": ""
    },
    {
        "id": 44,
        "url": "https://pub-7ef623b87169458aaafb3a91ab9b2966.r2.dev/full/20210527_绿洲-P_XZ-1.jpg",
        "date": "2021-05-27",
        "month": "May",
        "year": "2021",
        "tags": [
            "摄影"
        ],
        "link": "",
        "groupName": "202105",
        "note": "",
        "category": "attached",
        "source": "oasis",
        "photoText": ""
    },
    {
        "id": 45,
        "url": "https://pub-7ef623b87169458aaafb3a91ab9b2966.r2.dev/full/20210527_绿洲-P_XZ-3.jpg",
        "date": "2021-05-27",
        "month": "May",
        "year": "2021",
        "tags": [
            "小面包"
        ],
        "groupName": "202105",
        "category": "attached",
        "source": "oasis",
        "photoText": ""
    },
    {
        "id": 46,
        "url": "https://pub-7ef623b87169458aaafb3a91ab9b2966.r2.dev/full/20210527_绿洲-P_XZ-2.jpg",
        "date": "2021-05-27",
        "month": "May",
        "year": "2021",
        "tags": [
            "摄影"
        ],
        "link": "",
        "groupName": "202105",
        "note": "",
        "category": "attached",
        "source": "oasis",
        "photoText": ""
    },
    {
        "id": 47,
        "url": "https://pub-7ef623b87169458aaafb3a91ab9b2966.r2.dev/full/20210527_绿洲-P_XZ-4.jpg",
        "date": "2021-05-27",
        "month": "May",
        "year": "2021",
        "tags": [
            "小面包"
        ],
        "groupName": "202105",
        "category": "attached",
        "source": "oasis",
        "photoText": ""
    },
    {
        "id": 48,
        "url": "https://pub-7ef623b87169458aaafb3a91ab9b2966.r2.dev/full/20210527_DY_XZ.mp4",
        "date": "2021-05-27",
        "month": "May",
        "year": "2021",
        "tags": [
            "Video",
            "Run run run！"
        ],
        "category": "attached",
        "groupName": "202105",
        "source": "douyin",
        "link": "https://v.douyin.com/xP64RH0Jfqk/",
        "photoText": ""
    },
    {
        "id": 37,
        "url": "https://pub-7ef623b87169458aaafb3a91ab9b2966.r2.dev/full/20210515_绿洲_XZ.jpg",
        "date": "2021-05-15",
        "month": "May",
        "year": "2021",
        "tags": [],
        "category": "screenshot",
        "groupName": "202105",
        "source": "oasis",
        "photoText": "X玖少年团肖战 DAYTOY\n说到做到(压箱底存货)\n发布于2021/05/15 19:50\n在绿洲,分享美好生活"
    },
    {
        "id": 38,
        "url": "https://pub-7ef623b87169458aaafb3a91ab9b2966.r2.dev/full/20210515_绿洲-P_XZ-1.jpg",
        "date": "2021-05-15",
        "month": "May",
        "year": "2021",
        "tags": [
            "自拍"
        ],
        "link": "",
        "groupName": "202105",
        "note": "",
        "category": "attached",
        "source": "oasis",
        "photoText": ""
    },
    {
        "id": 39,
        "url": "https://pub-7ef623b87169458aaafb3a91ab9b2966.r2.dev/full/20210515_绿洲-P_XZ-2.jpg",
        "date": "2021-05-15",
        "month": "May",
        "year": "2021",
        "tags": [
            "自拍"
        ],
        "link": "",
        "groupName": "202105",
        "note": "",
        "category": "attached",
        "source": "oasis",
        "photoText": ""
    },
    {
        "id": 40,
        "url": "https://pub-7ef623b87169458aaafb3a91ab9b2966.r2.dev/full/20210515_绿洲-P_XZ-3.jpg",
        "date": "2021-05-15",
        "month": "May",
        "year": "2021",
        "tags": [
            "自拍"
        ],
        "link": "",
        "groupName": "202105",
        "note": "",
        "category": "attached",
        "source": "oasis",
        "photoText": ""
    },
    {
        "id": 41,
        "url": "https://pub-7ef623b87169458aaafb3a91ab9b2966.r2.dev/full/20210515_绿洲-P_XZ-4.jpg",
        "date": "2021-05-15",
        "month": "May",
        "year": "2021",
        "tags": [
            "奥特曼"
        ],
        "link": "",
        "groupName": "202105",
        "note": "",
        "category": "attached",
        "source": "oasis",
        "photoText": ""
    },
    {
        "id": 36,
        "url": "https://pub-7ef623b87169458aaafb3a91ab9b2966.r2.dev/full/20210430_DY_XZ.mp4",
        "date": "2021-04-30",
        "month": "April",
        "year": "2021",
        "tags": [
            "Video",
            "失控😅"
        ],
        "category": "attached",
        "groupName": "202104",
        "source": "douyin",
        "link": "https://v.douyin.com/cxbQl45o1Eg/ ",
        "photoText": ""
    },
    {
        "id": 34,
        "url": "https://pub-7ef623b87169458aaafb3a91ab9b2966.r2.dev/full/20210423_绿洲_XZ.jpg",
        "date": "2021-04-23",
        "month": "April",
        "year": "2021",
        "tags": [
            "有心",
            "手有玫瑰"
        ],
        "category": "screenshot",
        "groupName": "202104",
        "source": "oasis",
        "photoText": "X玖少年团肖战DAYTOY\n有心,春暖艳阳天。\n发布于2021/04/23 23:58\n在绿洲,分享美好生活"
    },
    {
        "id": 35,
        "url": "https://pub-7ef623b87169458aaafb3a91ab9b2966.r2.dev/full/20210423_绿洲-P_XZ.jpg",
        "date": "2021-04-23",
        "month": "April",
        "year": "2021",
        "tags": [
            "有心",
            "手有玫瑰"
        ],
        "groupName": "202104",
        "category": "attached",
        "source": "oasis",
        "photoText": ""
    },
    {
        "id": 32,
        "url": "https://pub-7ef623b87169458aaafb3a91ab9b2966.r2.dev/full/20210420-1_绿洲_XZ.jpg",
        "date": "2021-04-20",
        "month": "April",
        "year": "2021",
        "tags": [
            "小面包"
        ],
        "category": "screenshot",
        "groupName": "202104",
        "source": "oasis",
        "photoText": "X玖少年团肖战DAYTOY\n小面包又来害我了\n发布于2021/04/20 12:04\n在绿洲,分享美好生活"
    },
    {
        "id": 33,
        "url": "https://pub-7ef623b87169458aaafb3a91ab9b2966.r2.dev/full/20210420-1_绿洲-P_XZ.jpg",
        "date": "2021-04-20",
        "month": "April",
        "year": "2021",
        "tags": [
            "小面包"
        ],
        "groupName": "202104",
        "category": "attached",
        "source": "oasis",
        "photoText": ""
    },
    {
        "id": 30,
        "url": "https://pub-7ef623b87169458aaafb3a91ab9b2966.r2.dev/full/20210414_绿洲_XZ.jpg",
        "date": "2021-04-14",
        "month": "April",
        "year": "2021",
        "tags": [
            "岁岁平安"
        ],
        "category": "screenshot",
        "groupName": "202104",
        "source": "oasis",
        "photoText": "X玖少年团肖战DAYTOY\n岁岁平安\n发布于2021/04/14 20:21\n在绿洲,分享美好生活"
    },
    {
        "id": 31,
        "url": "https://pub-7ef623b87169458aaafb3a91ab9b2966.r2.dev/full/20210414_绿洲-P_XZ.jpg",
        "date": "2021-04-14",
        "month": "April",
        "year": "2021",
        "tags": [
            "岁岁平安"
        ],
        "groupName": "202104",
        "category": "attached",
        "source": "oasis",
        "photoText": ""
    },
    {
        "id": 29,
        "url": "https://pub-7ef623b87169458aaafb3a91ab9b2966.r2.dev/full/20210405_WB_XZ.jpg",
        "date": "2021-04-05",
        "month": "April",
        "year": "2021",
        "tags": [],
        "category": "screenshot",
        "groupName": "202104",
        "source": "weibo",
        "link": "",
        "note": "",
        "photoText": "肖战\nV\n4-5 07:57\n16年就说过,希望只在官方公开场合更好的相\n见。请你们不要再跟组,不要跟车跟机。在公\n路上追车或者故意慢速压我们的车,都非常的\n危险!不要半夜敲我的门、趴我门上偷听,更\n不要围堵在酒店了。昨天甚至出现了有人故意\n多次输错密码导致酒店楼层区域的密码锁打不\n开,无法回房间休息的情况,这非常影响我在\n剧组的工作。希望大家回归自己的生活,做好\n自己。\n3330"
    },
    {
        "id": 27,
        "url": "https://pub-7ef623b87169458aaafb3a91ab9b2966.r2.dev/full/20210319_如梦之梦_XZ.mp4",
        "date": "2021-03-19",
        "month": "March",
        "year": "2021",
        "tags": [
            "如梦之梦",
            "Video",
            "五号"
        ],
        "category": "attached",
        "groupName": "202103",
        "photoText": ""
    },
    {
        "id": 28,
        "url": "https://pub-7ef623b87169458aaafb3a91ab9b2966.r2.dev/full/20210319_DY_XZ.mp4",
        "date": "2021-03-19",
        "month": "March",
        "year": "2021",
        "tags": [
            "如梦之梦",
            "Video"
        ],
        "category": "attached",
        "groupName": "202103",
        "source": "douyin",
        "link": "https://v.douyin.com/jNBUVNAGh2M/ ",
        "photoText": ""
    },
    {
        "id": 22,
        "url": "https://pub-7ef623b87169458aaafb3a91ab9b2966.r2.dev/full/20210316_绿洲_XZ.jpg",
        "date": "2021-03-17",
        "month": "March",
        "year": "2021",
        "tags": [
            "随笔",
            "斗罗大陆",
            "收官",
            "完结"
        ],
        "category": "screenshot",
        "groupName": "202103",
        "source": "oasis",
        "photoText": "X玖少年团肖战DAYTOY\n零散随记\n2021年3月17日 上午12:24\n今天斗罗完结,需要一些当时的照片,赶紧\n打开手机翻当时的照片。翻了一页又一页,\n才发现,都已经过去2年了...\n2年的中间发生了很多事,唯一不变的还是\n想要不断的成长。\n照片、文字、音乐都有一种魔力,可以把\n你,瞬间拉回到那个当下时刻。有两张图片\n我很喜欢,一张是当时象山剧组酒店阳台外\n的沙滩,一张是每天奔波在,横店仙居树林\n间的高速路上的景观。两张不同地方甚至不\n同景色,但是都是在我无助和迷茫时,安抚\n我的地方。在我沮丧时,坐在阳台,深夜的\n海风和沙滩,还有月光,会给我答案;在我\n疲惫时,林间转场的路程可以小憩,睁开\n眼,车窗外的雨滴和云雾,也会给我答案:\n在每一个当下,选择不消极不埋怨,每一个\n决定和选择都全力以赴;在每一次的工作中\n照片、文字、音乐都有一种魔力,可以把\n你,瞬间拉回到那个当下时刻。有两张图片\n我很喜欢,一张是当时象山剧组酒店阳台外\n的沙滩,一张是每天奔波在,横店仙居树林\n间的高速路上的景观。两张不同地方甚至不\n同景色,但是都是在我无助和迷茫时,安抚\n我的地方。在我沮丧时,坐在阳台,深夜的\n海风和沙滩,还有月光,会给我答案;在我\n疲惫时,林间转场的路程可以小憩,睁开\n眼,车窗外的雨滴和云雾,也会给我答案:\n在每一个当下,选择不消极不埋怨,每一个\n决定和选择都全力以赴;在每一次的工作中\n找到自己的乐趣,这就够了。至少自己尽力\n了,不是吗?\n以前是,现在是,未来我想也是!\n————写在当下\n发布于2021/03/16 12:42\n在绿洲,遇见美好遇见你"
    },
    {
        "id": 23,
        "url": "https://pub-7ef623b87169458aaafb3a91ab9b2966.r2.dev/full/20210316_绿洲-P_XZ-1.jpg",
        "date": "2021-03-17",
        "month": "March",
        "year": "2021",
        "tags": [
            "随笔",
            "斗罗大陆",
            "收官",
            "完结"
        ],
        "groupName": "202103",
        "category": "attached",
        "source": "oasis",
        "photoText": "2021年3月17日 上午12:24\n零散随记\n今天斗罗完结,需要一些当时的照片,赶紧\n打开手机翻当时的照片。翻了一页又一页,\n才发现,都已经过去2年了...\n2年的中间发生了很多事,唯一不变的还是\n想要不断的成长。\n照片、文字、音乐都有一种魔力,可以把\n你,瞬间拉回到那个当下时刻。有两张图片\n我很喜欢,一张是当时象山剧组酒店阳台外\n的沙滩,一张是每天奔波在,横店仙居树林\n间的高速路上的景观。两张不同地方甚至不\n同景色,但是都是在我无助和迷茫时,安抚\n我的地方。在我沮丧时,坐在阳台,深夜的\n海风和沙滩,还有月光,会给我答案;在我\n疲惫时,林间转场的路程可以小憩,睁开\n眼,车窗外的雨滴和云雾,也会给我答案:\n在每一个当下,选择不消极不埋怨,每一个\n决定和选择都全力以赴;在每一次的工作中"
    },
    {
        "id": 24,
        "url": "https://pub-7ef623b87169458aaafb3a91ab9b2966.r2.dev/full/20210316_绿洲-P_XZ-3.jpg",
        "date": "2021-03-17",
        "month": "March",
        "year": "2021",
        "tags": [
            "摄影",
            "斗罗大陆",
            "收官",
            "完结"
        ],
        "link": "",
        "groupName": "202103",
        "note": "",
        "category": "attached",
        "source": "oasis",
        "photoText": ""
    },
    {
        "id": 25,
        "url": "https://pub-7ef623b87169458aaafb3a91ab9b2966.r2.dev/full/20210316_绿洲-P_XZ-2.jpg",
        "date": "2021-03-17",
        "month": "March",
        "year": "2021",
        "tags": [
            "随笔",
            "斗罗大陆",
            "收官",
            "完结"
        ],
        "groupName": "202103",
        "category": "attached",
        "source": "oasis",
        "photoText": "照片、文字、音乐都有一种魔力,可以把\n你,瞬间拉回到那个当下时刻。有两张图片\n我很喜欢,一张是当时象山剧组酒店阳台外\n的沙滩,一张是每天奔波在,横店仙居树林\n间的高速路上的景观。两张不同地方甚至不\n同景色,但是都是在我无助和迷茫时,安抚\n我的地方。在我沮丧时,坐在阳台,深夜的\n海风和沙滩,还有月光,会给我答案;在我\n疲惫时,林间转场的路程可以小憩,睁开\n眼,车窗外的雨滴和云雾,也会给我答案:\n在每一个当下,选择不消极不埋怨,每一个\n决定和选择都全力以赴;在每一次的工作中\n找到自己的乐趣,这就够了。至少自己尽力\n了,不是吗?\n以前是,现在是,未来我想也是!\n————写在当下"
    },
    {
        "id": 26,
        "url": "https://pub-7ef623b87169458aaafb3a91ab9b2966.r2.dev/full/20210316_绿洲-P_XZ-4.jpg",
        "date": "2021-03-17",
        "month": "March",
        "year": "2021",
        "tags": [
            "摄影",
            "斗罗大陆",
            "收官",
            "完结"
        ],
        "link": "",
        "groupName": "202103",
        "note": "",
        "category": "attached",
        "source": "oasis",
        "photoText": ""
    },
    {
        "id": 21,
        "url": "https://pub-7ef623b87169458aaafb3a91ab9b2966.r2.dev/full/20210305_雷锋日记_XZ.mp4",
        "date": "2021-03-05",
        "month": "March",
        "year": "2021",
        "tags": [
            "雷锋日记",
            "Video"
        ],
        "category": "attached",
        "groupName": "202103",
        "photoText": ""
    },
    {
        "id": 19,
        "url": "https://pub-7ef623b87169458aaafb3a91ab9b2966.r2.dev/full/20210302_绿洲_XZ.jpg",
        "date": "2021-03-02",
        "month": "March",
        "year": "2021",
        "tags": [
            "想念",
            "画"
        ],
        "category": "screenshot",
        "groupName": "202103",
        "source": "oasis",
        "link": "",
        "note": "",
        "photoText": "X玖少年团肖战DAYTOY\n想念\n发布于2021/03/02 21:02\n在绿洲,遇见美好遇见你\n2.\n2024-3-3"
    },
    {
        "id": 20,
        "url": "https://pub-7ef623b87169458aaafb3a91ab9b2966.r2.dev/full/20210302_绿洲-P_XZ.jpg",
        "date": "2021-03-02",
        "month": "March",
        "year": "2021",
        "tags": [
            "想念",
            "画"
        ],
        "link": "",
        "groupName": "202103",
        "note": "",
        "category": "attached",
        "source": "oasis",
        "photoText": "2-\n2020.3.3"
    },
    {
        "id": 18,
        "url": "https://pub-7ef623b87169458aaafb3a91ab9b2966.r2.dev/full/20210213_DY_XZ.mp4",
        "date": "2021-02-13",
        "month": "February",
        "year": "2021",
        "tags": [
            "Video",
            "情人节"
        ],
        "category": "attached",
        "groupName": "202102",
        "source": "douyin",
        "link": "https://v.douyin.com/UMT-VTHF-Dc/",
        "photoText": ""
    },
    {
        "id": 17,
        "url": "https://pub-7ef623b87169458aaafb3a91ab9b2966.r2.dev/full/20210212_DY_XZ.mp4",
        "date": "2021-02-12",
        "month": "February",
        "year": "2021",
        "tags": [
            "Video",
            "斗罗大陆"
        ],
        "category": "attached",
        "groupName": "202102",
        "source": "douyin",
        "link": "https://v.douyin.com/i205ZBDMgek/",
        "photoText": ""
    },
    {
        "id": 14,
        "url": "https://pub-7ef623b87169458aaafb3a91ab9b2966.r2.dev/full/20210211_绿洲_XZ.jpg",
        "date": "2021-02-11",
        "month": "February",
        "year": "2021",
        "tags": [
            "新年",
            "牛年",
            "剪纸"
        ],
        "category": "screenshot",
        "groupName": "202102",
        "source": "oasis",
        "photoText": "X玖少年团肖战DAYTOY\n新年快乐!!! #牛年如意 福福福牛!!\n发布于2021/02/11 04:34\n在绿洲,遇见美好遇见你"
    },
    {
        "id": 15,
        "url": "https://pub-7ef623b87169458aaafb3a91ab9b2966.r2.dev/full/20210211_绿洲-P_XZ-2.jpg",
        "date": "2021-02-11",
        "month": "February",
        "year": "2021",
        "tags": [
            "新年",
            "牛年",
            "剪纸"
        ],
        "groupName": "202102",
        "category": "attached",
        "source": "oasis",
        "photoText": ""
    },
    {
        "id": 16,
        "url": "https://pub-7ef623b87169458aaafb3a91ab9b2966.r2.dev/full/20210211_绿洲-P_XZ-1.jpg",
        "date": "2021-02-11",
        "month": "February",
        "year": "2021",
        "tags": [
            "新年",
            "牛年",
            "剪纸",
            "自拍"
        ],
        "link": "",
        "groupName": "202102",
        "note": "",
        "category": "attached",
        "source": "oasis",
        "photoText": ""
    },
    {
        "id": 11,
        "url": "https://pub-7ef623b87169458aaafb3a91ab9b2966.r2.dev/full/20210206_绿洲_XZ.jpg",
        "date": "2021-02-06",
        "month": "February",
        "year": "2021",
        "tags": [
            "蓝银皮皮草"
        ],
        "category": "screenshot",
        "groupName": "202102",
        "source": "oasis",
        "photoText": "X玖少年团肖战DAYTOY\n蓝银皮皮草!\n发布于2021/02/06 23:00\n在绿洲,遇见美好遇见你"
    },
    {
        "id": 12,
        "url": "https://pub-7ef623b87169458aaafb3a91ab9b2966.r2.dev/full/20210206_绿洲-P_XZ-2.jpg",
        "date": "2021-02-06",
        "month": "February",
        "year": "2021",
        "tags": [
            "蓝银皮皮草",
            "自拍"
        ],
        "link": "",
        "groupName": "202102",
        "note": "",
        "category": "attached",
        "source": "oasis",
        "photoText": ""
    },
    {
        "id": 13,
        "url": "https://pub-7ef623b87169458aaafb3a91ab9b2966.r2.dev/full/20210206_绿洲-P_XZ-1.jpg",
        "date": "2021-02-06",
        "month": "February",
        "year": "2021",
        "tags": [
            "蓝银皮皮草",
            "自拍"
        ],
        "link": "",
        "groupName": "202102",
        "note": "",
        "category": "attached",
        "source": "oasis",
        "photoText": "9119"
    },
    {
        "id": 10,
        "url": "https://pub-7ef623b87169458aaafb3a91ab9b2966.r2.dev/full/20210205_DY_XZ.mp4",
        "date": "2021-02-05",
        "month": "February",
        "year": "2021",
        "tags": [
            "Video",
            "斗罗大陆"
        ],
        "category": "attached",
        "source": "douyin",
        "link": "https://v.douyin.com/1RtT0_YYKRo/",
        "groupName": "202102",
        "photoText": ""
    },
    {
        "id": 9,
        "url": "https://pub-7ef623b87169458aaafb3a91ab9b2966.r2.dev/full/20210127_DY_XZ.mp4",
        "date": "2021-01-27",
        "month": "January",
        "year": "2021",
        "tags": [
            "Video",
            "清库存…🤪"
        ],
        "category": "attached",
        "groupName": "202101",
        "source": "douyin",
        "link": "https://v.douyin.com/w5W8CYgpy2M/",
        "note": "",
        "photoText": ""
    },
    {
        "id": 6,
        "url": "https://pub-7ef623b87169458aaafb3a91ab9b2966.r2.dev/full/20210122绿洲_XZ.jpg",
        "date": "2021-01-22",
        "month": "January",
        "year": "2021",
        "tags": [
            "画",
            "自画像"
        ],
        "category": "screenshot",
        "groupName": "202101",
        "source": "oasis",
        "photoText": "X玖少年团肖战DAYTOY\n没想到吧\n没想到吧\n发布于2021/01/22 00:19\n在绿洲,遇见美好遇见你"
    },
    {
        "id": 7,
        "url": "https://pub-7ef623b87169458aaafb3a91ab9b2966.r2.dev/full/20210122_绿洲-P_XZ-2.jpg",
        "date": "2021-01-22",
        "month": "January",
        "year": "2021",
        "tags": [
            "表情包",
            "猫",
            "没想到吧"
        ],
        "link": "",
        "groupName": "202101",
        "note": "",
        "category": "attached",
        "source": "oasis",
        "photoText": "没想到吧"
    },
    {
        "id": 8,
        "url": "https://pub-7ef623b87169458aaafb3a91ab9b2966.r2.dev/full/20210122_绿洲-P_XZ-1.jpg",
        "date": "2021-01-22",
        "month": "January",
        "year": "2021",
        "tags": [
            "画",
            "自画像"
        ],
        "groupName": "202101",
        "category": "attached",
        "source": "oasis",
        "photoText": ""
    },
    {
        "id": 4,
        "url": "https://pub-7ef623b87169458aaafb3a91ab9b2966.r2.dev/full/20210121_绿洲_XZ.jpg",
        "date": "2021-01-21",
        "month": "January",
        "year": "2021",
        "tags": [
            "画",
            "自画像"
        ],
        "category": "screenshot",
        "source": "oasis",
        "groupName": "202101",
        "photoText": "X玖少年团肖战DAYTOY\n我也不知道画了个啥\n发布于2021/01/21 19:39\n在绿洲,遇见美好遇见你"
    },
    {
        "id": 5,
        "url": "https://pub-7ef623b87169458aaafb3a91ab9b2966.r2.dev/full/20210121_绿洲-P_XZ-1.jpg",
        "date": "2021-01-21",
        "month": "January",
        "year": "2021",
        "tags": [
            "画",
            "自画像"
        ],
        "groupName": "202101",
        "category": "attached",
        "source": "oasis",
        "photoText": ""
    },
    {
        "id": 3,
        "url": "https://pub-7ef623b87169458aaafb3a91ab9b2966.r2.dev/full/20210117_DY_XZ.mp4",
        "date": "2021-01-17",
        "month": "January",
        "year": "2021",
        "tags": [
            "再哈一次哈哈哈哈哈哈哈哈😏",
            "Video"
        ],
        "category": "attached",
        "groupName": "202101",
        "source": "douyin",
        "link": "https://v.douyin.com/auCOjEqMtxs/",
        "photoText": ""
    },
    {
        "id": 1,
        "url": "https://pub-7ef623b87169458aaafb3a91ab9b2966.r2.dev/full/20210115_绿洲_XZ.jpg",
        "date": "2021-01-15",
        "month": "January",
        "year": "2021",
        "tags": [
            "新的一天",
            "刚睡醒"
        ],
        "category": "screenshot",
        "source": "oasis",
        "groupName": "202101",
        "link": "",
        "note": "",
        "photoText": "X玖少年团肖战DAYTOY\n刚睡醒,什么事\n新的一天!元气满满!\n发布于2021/01/15 11:14\n在绿洲,遇见美好遇见你"
    },
    {
        "id": 2,
        "url": "https://pub-7ef623b87169458aaafb3a91ab9b2966.r2.dev/full/20210115_绿洲-P_XZ.jpg",
        "date": "2021-01-15",
        "month": "January",
        "year": "2021",
        "tags": [
            "新的一天",
            "刚睡醒",
            "表情包"
        ],
        "link": "",
        "groupName": "202101",
        "note": "",
        "category": "attached",
        "source": "oasis",
        "photoText": "刚睡醒，什么事"
    }
]